networkdiagram/__init__.py
networkdiagram/networkdiagram.py
networkdiagram-1.9.1.dist-info/LICENSE
networkdiagram-1.9.1.dist-info/METADATA
networkdiagram-1.9.1.dist-info/WHEEL
networkdiagram-1.9.1.dist-info/top_level.txt
networkdiagram-1.9.1.dist-info/RECORD
