Metadata-Version: 2.1
Name: networkdiagram
Version: 1.9.1
Summary: A Python library for creating, calculating, and visualizing CPM/PERT Network Diagrams.
Home-page: UNKNOWN
Author: Kathan Majithia
Author-email: kathanmajithia@gmail.com
License: MIT
Platform: UNKNOWN
Classifier: License :: OSI Approved :: MIT License
Classifier: Programming Language :: Python :: 3
Classifier: Programming Language :: Python :: 3.8
Classifier: Operating System :: OS Independent
Requires-Dist: networkx
Requires-Dist: matplotlib
